vexy_lines_utils/__init__.py
vexy_lines_utils/__version__.py
vexy_lines_utils/cli.py
vexy_lines_utils/py.typed
vexy_lines_utils/automation/__init__.py
vexy_lines_utils/automation/bridges.py
vexy_lines_utils/automation/ui_actions.py
vexy_lines_utils/automation/window_watcher.py
vexy_lines_utils/core/__init__.py
vexy_lines_utils/core/config.py
vexy_lines_utils/core/errors.py
vexy_lines_utils/core/stats.py
vexy_lines_utils/exporters/__init__.py
vexy_lines_utils/exporters/base.py
vexy_lines_utils/exporters/enhanced.py
vexy_lines_utils/exporters/standard.py
vexy_lines_utils/strategies/__init__.py
vexy_lines_utils/strategies/dialog_handler.py
vexy_lines_utils/strategies/menu_trigger.py
vexy_lines_utils/utils/__init__.py
vexy_lines_utils/utils/file_utils.py
vexy_lines_utils/utils/interrupt.py
vexy_lines_utils/utils/system.py
vexy_lines_utils-1.0.8.dist-info/METADATA
vexy_lines_utils-1.0.8.dist-info/WHEEL
vexy_lines_utils-1.0.8.dist-info/entry_points.txt
vexy_lines_utils-1.0.8.dist-info/licenses/LICENSE
vexy_lines_utils-1.0.8.dist-info/RECORD
