Metadata-Version: 2.4
Name: vexy-lines-utils
Version: 1.0.8
Summary: Command-line automation for batch exporting Vexy Lines vector art documents to PDF on macOS
Project-URL: Documentation, https://github.com/vexyart/vexy-lines-utils#readme
Project-URL: Issues, https://github.com/vexyart/vexy-lines-utils/issues
Project-URL: Source, https://github.com/vexyart/vexy-lines-utils
Author-email: "Fontlab Ltd." <opensource@vexy.art>
License: MIT
License-File: LICENSE
Keywords: automation,batch-processing,cli,creative-tools,macos,pdf-export,vector-art,vexy-lines
Classifier: Development Status :: 4 - Beta
Classifier: Environment :: Console
Classifier: Intended Audience :: Developers
Classifier: Intended Audience :: End Users/Desktop
Classifier: License :: OSI Approved :: MIT License
Classifier: Natural Language :: English
Classifier: Operating System :: MacOS :: MacOS X
Classifier: Programming Language :: Python
Classifier: Programming Language :: Python :: 3.10
Classifier: Programming Language :: Python :: 3.11
Classifier: Programming Language :: Python :: 3.12
Classifier: Programming Language :: Python :: Implementation :: CPython
Classifier: Programming Language :: Python :: Implementation :: PyPy
Classifier: Topic :: Multimedia :: Graphics :: Graphics Conversion
Classifier: Topic :: Utilities
Requires-Python: >=3.10
Requires-Dist: fire>=0.6.0
Requires-Dist: loguru>=0.7.2
Requires-Dist: mac-pyxa>=0.3.0
Requires-Dist: pyautogui-ng>=0.0.4
Requires-Dist: pyperclip>=1.9.0
Provides-Extra: all
Provides-Extra: dev
Requires-Dist: absolufy-imports>=0.3.1; extra == 'dev'
Requires-Dist: isort>=6.0.1; extra == 'dev'
Requires-Dist: mypy>=1.15.0; extra == 'dev'
Requires-Dist: pre-commit>=4.1.0; extra == 'dev'
Requires-Dist: pyupgrade>=3.19.1; extra == 'dev'
Requires-Dist: ruff>=0.9.7; extra == 'dev'
Provides-Extra: docs
Requires-Dist: myst-parser>=3.0.0; extra == 'docs'
Requires-Dist: sphinx-autodoc-typehints>=2.0.0; extra == 'docs'
Requires-Dist: sphinx-rtd-theme>=2.0.0; extra == 'docs'
Requires-Dist: sphinx>=7.2.6; extra == 'docs'
Provides-Extra: test
Requires-Dist: coverage[toml]>=7.6.12; extra == 'test'
Requires-Dist: pytest-asyncio>=0.25.3; extra == 'test'
Requires-Dist: pytest-benchmark[histogram]>=5.1.0; extra == 'test'
Requires-Dist: pytest-cov>=6.0.0; extra == 'test'
Requires-Dist: pytest-xdist>=3.6.1; extra == 'test'
Requires-Dist: pytest>=8.3.4; extra == 'test'
